agent_types/__init__.py
agent_types/common.py
agent_types/config.py
agent_types/execution.py
agent_types/intent.py
agent_types/personalization.py
agent_types/planning.py
agent_types/retrieval.py
agent_types/summarization.py
agent_types/utils.py
agent_types/knowledge/__init__.py
agent_types/knowledge/augmentation.py
agent_types/knowledge/chunking.py
agent_types/knowledge/misc.py
agent_types/knowledge/parsing.py
agent_types/memory/__init__.py
agent_types/memory/session.py
agent_types/memory/system.py
agent_types/memory/user.py
agent_types-1.27.0.dist-info/METADATA
agent_types-1.27.0.dist-info/WHEEL
agent_types-1.27.0.dist-info/top_level.txt
agent_types-1.27.0.dist-info/zip-safe
agent_types-1.27.0.dist-info/RECORD
