Metadata-Version: 2.4
Name: agent_types
Version: 1.27.0
Summary: This package defines the interface of AI agent modules.
Author: xi
Author-email: gylv@mail.ustc.edu.cn
License: Apache-2.0 license
Platform: any
Classifier: Programming Language :: Python :: 3
Requires-Python: >=3.8
Requires-Dist: pydantic
Requires-Dist: numpy
Requires-Dist: scipy
Dynamic: author
Dynamic: author-email
Dynamic: classifier
Dynamic: description
Dynamic: description-content-type
Dynamic: license
Dynamic: platform
Dynamic: requires-dist
Dynamic: requires-python
Dynamic: summary
